llama_index/callbacks/openinference/__init__.py
llama_index/callbacks/openinference/base.py
llama_index_callbacks_openinference-0.4.1.dist-info/METADATA
llama_index_callbacks_openinference-0.4.1.dist-info/WHEEL
llama_index_callbacks_openinference-0.4.1.dist-info/licenses/LICENSE
llama_index_callbacks_openinference-0.4.1.dist-info/RECORD
